print_nest.py
print_nest-1.3.0.dist-info/LICENSE.txt
print_nest-1.3.0.dist-info/METADATA
print_nest-1.3.0.dist-info/WHEEL
print_nest-1.3.0.dist-info/top_level.txt
print_nest-1.3.0.dist-info/RECORD
