Metadata-Version: 2.1
Name: print-nest
Version: 1.3.0
Summary: a little tool for printing nested list.
Home-page: https://github.com/Mokusama
Author: GiantFurosemide
Author-email: 18640057101@163.com
License: UNKNOWN
Platform: UNKNOWN
Classifier: Programming Language :: Python :: 3
Classifier: License :: OSI Approved :: MIT License
Classifier: Operating System :: MacOS
